plpy/__init__.py
plpy/scripts.py
plpy/utils.py
plpy/bak/operations.py
plpy/bak/utils.py
plpy/bfosc/__init__.py
plpy/bfosc/imaging.py
plpy/bfosc/longslit.py
plpy/bfosc/scripts.py
plpy/bfosc/bak/drpy_bfosc_g4_comet_2020.py
plpy/bfosc/bak/drpy_bfosc_g4_slit23_general.py
plpy/bfosc/bak/drpy_bfosc_g4_slit23_general_2021.py
plpy/bfosc/bak/drpy_bfosc_g4_slit23_general_2022.py
plpy/bfosc/bak/drpy_bfosc_g4_slit23_standard.py
plpy/bfosc/bak/imaging_old.py
plpy/bfosc/bak/longslit_old.py
plpy/bfosc/lib/bfosc_g3_slit18_2024a.fits
plpy/bfosc/lib/bfosc_g3_slit23_2024a.fits
plpy/bfosc/lib/bfosc_g4_slit18_2020a.fits
plpy/bfosc/lib/bfosc_g4_slit23_2020a.fits
plpy/bfosc/lib/bfosc_g4_slit23_2022b.fits
plpy/bfosc/lib/bfosc_g4_slit23_2022b.fits.bak
plpy/bfosc/lib/params.toml
plpy/bfosc/lib/2020a/bfosc_g4_slit18_2020a.reg
plpy/bfosc/lib/2020a/bfosc_g4_slit23_2020a.reg
plpy/bfosc/lib/2021b/bfosc_g4_slit23_2021b.reg
plpy/bfosc/lib/2022b/bfosc_g4_slit23_2022b.reg
plpy/bfosc/lib/2023b/bfosc_g4_slit18_2023b.reg
plpy/bfosc/lib/2023b/bfosc_g4_slit23_2023b.reg
plpy/fire/__init__.py
plpy/fire/scripts.py
plpy/fire/utils.py
plpy/fire/lib/fire_arc_2023a.fits
plpy/fire/lib/fire_flat_2023b.reg
plpy/fire/lib/params.toml
plpy/hrs/__init__.py
plpy/hrs/scripts.py
plpy/hrs/utils.py
plpy/hrs/lib/order.npy
plpy/hrs/lib/params.toml
plpy/hrs/lib/profile.npy
plpy/mst/__init__.py
plpy/mst/scripts.py
plpy/mst/lib/params.toml
plpy/tspec/__init__.py
plpy/tspec/scripts.py
plpy/tspec/lib/params.toml
plpy/tspec/lib/tspec_order_3.fits
plpy/tspec/lib/tspec_order_4.fits
plpy/tspec/lib/tspec_order_5.fits
plpy/tspec/lib/tspec_order_6.fits
plpy/tspec/lib/tspec_order_7.fits
plpy/yfosc/__init__.py
plpy/yfosc/scripts.py
plpy/yfosc/lib/params.toml
plpy/yfosc/lib/yfosc_g3_slit25_2020.fits
astro_plpy-1.0.1.dist-info/LICENSE
astro_plpy-1.0.1.dist-info/METADATA
astro_plpy-1.0.1.dist-info/WHEEL
astro_plpy-1.0.1.dist-info/entry_points.txt
astro_plpy-1.0.1.dist-info/top_level.txt
astro_plpy-1.0.1.dist-info/RECORD
