Metadata-Version: 2.2
Name: astro-plpy
Version: 1.0.1
Summary: Data reduction pipelines developed based on astro-drpy.
Author-email: Ruining ZHAO <ruiningzhao@mail.bnu.edu.cn>
Project-URL: Homepage, https://github.com/RuiningZHAO/plpy
Project-URL: Tracker, https://github.com/RuiningZHAO/plpy/issues
Classifier: Programming Language :: Python :: 3
Classifier: License :: OSI Approved :: GNU General Public License v3 (GPLv3)
Classifier: Operating System :: OS Independent
Requires-Python: >=3.7.3
License-File: LICENSE
Requires-Dist: astro-drpy>=0.1.9
Requires-Dist: pyregion>=2.2.0
